decologr/__init__.py
decologr/logger.py
decologr/viewer.py
decologr/tests/__init__.py
decologr/tests/test_rich_integration.py
decologr-0.3.3.dist-info/licenses/LICENSE
decologr-0.3.3.dist-info/METADATA
decologr-0.3.3.dist-info/WHEEL
decologr-0.3.3.dist-info/top_level.txt
decologr-0.3.3.dist-info/RECORD
