Metadata-Version: 2.4
Name: decologr
Version: 0.3.3
Summary: Decorative Logger - A logging utility with emoji decorations
Author: Mark Brooks
License: MIT
Classifier: Development Status :: 3 - Alpha
Classifier: Intended Audience :: Developers
Classifier: License :: OSI Approved :: MIT License
Classifier: Operating System :: OS Independent
Classifier: Programming Language :: Python :: 3
Classifier: Programming Language :: Python :: 3.10
Classifier: Programming Language :: Python :: 3.11
Classifier: Programming Language :: Python :: 3.12
Classifier: Programming Language :: Python :: 3.13
Requires-Python: >=3.10
License-File: LICENSE
Provides-Extra: numpy
Requires-Dist: numpy>=1.20.0; extra == "numpy"
Provides-Extra: rich
Requires-Dist: rich>=13.0.0; extra == "rich"
Provides-Extra: textual
Requires-Dist: textual>=0.40.0; extra == "textual"
Provides-Extra: all
Requires-Dist: numpy>=1.20.0; extra == "all"
Requires-Dist: rich>=13.0.0; extra == "all"
Requires-Dist: textual>=0.40.0; extra == "all"
Dynamic: license-file
